<?xml version="1.0" encoding="utf-8"?>
<calculation-relax-static><key>96050b09-4c51-4f74-bd77-deb03e020ac6</key><calculation><iprPy-version>0.8.3</iprPy-version><atomman-version>1.2.4</atomman-version><LAMMPS-version>22 Aug 2018</LAMMPS-version><script>calc_relax_static</script><run-parameter><size-multipliers><a>0</a><a>1</a><b>0</b><b>1</b><c>0</c><c>1</c></size-multipliers><energytolerance>0.0</energytolerance><forcetolerance><value>1e-10</value><unit>eV/angstrom</unit></forcetolerance><maxiterations>10000</maxiterations><maxevaluations>100000</maxevaluations><maxatommotion><value>0.01</value><unit>angstrom</unit></maxatommotion></run-parameter></calculation><potential-LAMMPS><key>8ffc1d8f-8b64-4d14-8803-86a83121628c</key><id>2011--Bonny-G--Fe-Ni-Cr--LAMMPS--ipr1</id><potential><key>17676f3f-5287-4bb9-892a-0bfe9b1fb160</key><id>2011--Bonny-G-Terentyev-D-Pasianot-R-C-et-al--Fe-Ni-Cr</id></potential></potential-LAMMPS><system-info><family>A1--Cu--fcc</family><artifact><file>5d339b00-3184-4011-b711-4d1206e6bd14/10000.dump</file><format>atom_dump</format><load_options></load_options></artifact><symbol>Fe</symbol></system-info><phase-state><temperature><value>0.0</value><unit>K</unit></temperature><pressure-xx><value>0.0</value><unit>GPa</unit></pressure-xx><pressure-yy><value>0.0</value><unit>GPa</unit></pressure-yy><pressure-zz><value>0.0</value><unit>GPa</unit></pressure-zz><pressure-xy><value>0.0</value><unit>GPa</unit></pressure-xy><pressure-xz><value>0.0</value><unit>GPa</unit></pressure-xz><pressure-yz><value>0.0</value><unit>GPa</unit></pressure-yz></phase-state><initial-system><artifact><file>initial.dump</file><format>atom_dump</format></artifact><symbols>Fe</symbols></initial-system><final-system><artifact><file>relax_static-2.dump</file><format>atom_dump</format></artifact><symbols>Fe</symbols></final-system><measured-box-parameter><lx><value>34.9869653608446</value><unit>angstrom</unit></lx><ly><value>34.9869653608447</value><unit>angstrom</unit></ly><lz><value>34.9869653608447</value><unit>angstrom</unit></lz><xy><value>0.0</value><unit>angstrom</unit></xy><xz><value>0.0</value><unit>angstrom</unit></xz><yz><value>0.0</value><unit>angstrom</unit></yz></measured-box-parameter><measured-phase-state><temperature><value>0.0</value><unit>K</unit></temperature><pressure-xx><value>1.2465074112558003e-06</value><unit>GPa</unit></pressure-xx><pressure-yy><value>1.2465073090048e-06</value><unit>GPa</unit></pressure-yy><pressure-zz><value>1.2465073111429e-06</value><unit>GPa</unit></pressure-zz><pressure-xy><value>-2.9489004439951e-15</value><unit>GPa</unit></pressure-xy><pressure-xz><value>8.672259333889701e-16</value><unit>GPa</unit></pressure-xz><pressure-yz><value>-8.5382089651151e-15</value><unit>GPa</unit></pressure-yz></measured-phase-state><cohesive-energy><value>-4.1166314202092495</value><unit>eV</unit></cohesive-energy></calculation-relax-static>